{"id":"56ff1666-d3a2-456c-858b-08d36d4b8d4d","contract_id":"75bab805-2313-4b71-b698-39304436fb9a","name":"Munson's Pickles Fabric & Power BI","client_name":"Munson's Pickles & Preserves","project_manager":"Sophie Laurent","technical_lead":"Raj Patel","overall_health":"green","health_schedule":"green","health_budget":"green","health_scope":"green","health_risk":"green","health_satisfaction":"green","status":"completed","start_date":"2025-09-07","end_date":"2026-05-07","budget":920000.0,"actuals":890000.0,"burn_rate":96.7,"completion_pct":100,"phase":"close","executive_summary":"Project delivered on time and under budget. Production dashboard live. Erik Munson gave 10/10 CSAT. Reference customer secured.","created_at":"2026-05-05T22:40:03.319939","updated_at":"2026-05-05T22:40:03.319939","milestone_count":6,"open_raid_count":0}